datature/__main__.py
datature/nexus/__init__.py
datature/nexus/client.py
datature/nexus/client_context.py
datature/nexus/config.py
datature/nexus/error.py
datature/nexus/models.py
datature/nexus/requester.py
datature/nexus/version.py
datature/nexus/api/__init__.py
datature/nexus/api/artifact.py
datature/nexus/api/deployment.py
datature/nexus/api/object.py
datature/nexus/api/ontology.py
datature/nexus/api/operation.py
datature/nexus/api/prediction.py
datature/nexus/api/project.py
datature/nexus/api/run.py
datature/nexus/api/sequence.py
datature/nexus/api/tag.py
datature/nexus/api/types.py
datature/nexus/api/workflow.py
datature/nexus/api/annotation/__init__.py
datature/nexus/api/annotation/annotation.py
datature/nexus/api/annotation/import_session.py
datature/nexus/api/asset/__init__.py
datature/nexus/api/asset/asset.py
datature/nexus/api/asset/downloader.py
datature/nexus/api/asset/multipart.py
datature/nexus/api/asset/results.py
datature/nexus/api/asset/upload_session.py
datature/nexus/api/batch/__init__.py
datature/nexus/api/batch/batch.py
datature/nexus/api/batch/dataset.py
datature/nexus/api/batch/job.py
datature/nexus/api/batch/models.py
datature/nexus/api/batch/types.py
datature/nexus/api/batch/webhook.py
datature/nexus/cli/__init__.py
datature/nexus/cli/commands.py
datature/nexus/cli/config.py
datature/nexus/cli/consts.py
datature/nexus/cli/functions.py
datature/nexus/cli/main.py
datature/nexus/cli/messages.py
datature/nexus/cli/batch/__init__.py
datature/nexus/cli/batch/dataset.py
datature/nexus/cli/batch/functions.py
datature/nexus/cli/batch/job.py
datature/nexus/cli/batch/webhook.py
datature/nexus/cli/deploy/local/__init__.py
datature/nexus/cli/deploy/local/api.py
datature/nexus/cli/deploy/local/config.py
datature/nexus/cli/deploy/local/consts.py
datature/nexus/cli/deploy/local/endpoints.py
datature/nexus/cli/deploy/local/functions.py
datature/nexus/cli/deploy/local/logger.py
datature/nexus/cli/deploy/local/server.py
datature-1.11.7.dist-info/LICENSE
datature-1.11.7.dist-info/METADATA
datature-1.11.7.dist-info/WHEEL
datature-1.11.7.dist-info/entry_points.txt
datature-1.11.7.dist-info/top_level.txt
datature-1.11.7.dist-info/RECORD
