Metadata-Version: 2.1
Name: datature
Version: 1.11.7
Summary: Python bindings for the Datature API
Home-page: https://datature.io/
Author: Datature
Author-email: developers@datature.io
License: Apache License 2.0
Project-URL: Homepage, https://datature.io/
Project-URL: Documentation, https://developers.datature.io/docs/python-sdk
Project-URL: Download, https://pypi.org/project/datature#files
Project-URL: Changelog, https://developers.datature.io/docs/sdk-changelog
Project-URL: Slack Community, https://datature.io/community
Classifier: Programming Language :: Python
Classifier: Programming Language :: Python :: 3
Classifier: Programming Language :: Python :: 3.8
Classifier: Programming Language :: Python :: 3.9
Classifier: Programming Language :: Python :: 3.10
Classifier: Programming Language :: Python :: 3.11
Classifier: Programming Language :: Python :: 3.12
Classifier: License :: OSI Approved :: Apache Software License
Requires-Python: >=3.8
License-File: LICENSE
Requires-Dist: alive-progress==3.1.5
Requires-Dist: crc32c>=2.7.post1
Requires-Dist: cryptography==44.0.1
Requires-Dist: dateparser>=1.2.0
Requires-Dist: filetype==1.2.0
Requires-Dist: halo==0.0.31
Requires-Dist: inquirerpy==0.3.4
Requires-Dist: ipywidgets>=8.0.0
Requires-Dist: litserve>=0.2.12
Requires-Dist: matplotlib>=3.5.3
Requires-Dist: msgspec>=0.18.4
Requires-Dist: nibabel>=4.0.2
Requires-Dist: numpy<2.0.0,>=1.17.3
Requires-Dist: opencv-python<5.0.0,>=4.7.0.72
Requires-Dist: Pillow>=9.5.0
Requires-Dist: protobuf==5.29.5
Requires-Dist: pycocotools>=2.0.7
Requires-Dist: pydicom>=2.3.1
Requires-Dist: pytz>=2024.1
Requires-Dist: pyyaml>=6.0.0
Requires-Dist: requests>=2.28.1
Requires-Dist: scipy>=1.10.1
Requires-Dist: tqdm>=4.66.0
